{
    "xsize": 16,
    "zsize": 16,
    "palette": {
        "palette": [
            {
                "char": " ",
                "block": "minecraft:air"
            },
            {
                "char": "α",
                "block": "minecraft:stone_bricks"
            },
            {
                "char": "β",
                "block": "minecraft:mossy_stone_bricks"
            },
            {
                "char": "γ",
                "block": "minecraft:cracked_stone_bricks"
            },
            {
                "char": "δ",
                "block": "minecraft:grass_block[snowy=false]"
            },
            {
                "char": "ε",
                "block": "minecraft:iron_bars[east=true,north=false,south=true,waterlogged=false,west=false]"
            },
            {
                "char": "ζ",
                "block": "minecraft:iron_bars[east=false,north=false,south=true,waterlogged=false,west=true]"
            },
            {
                "char": "η",
                "block": "minecraft:iron_bars[east=true,north=true,south=false,waterlogged=false,west=false]"
            },
            {
                "char": "θ",
                "block": "minecraft:iron_bars[east=false,north=true,south=false,waterlogged=false,west=true]"
            },
            {
                "char": "ι",
                "block": "minecraft:iron_bars[east=false,north=false,south=false,waterlogged=false,west=true]"
            },
            {
                "char": "κ",
                "block": "minecraft:iron_bars[east=true,north=false,south=false,waterlogged=false,west=false]"
            },
            {
                "char": "λ",
                "block": "minecraft:iron_bars[east=false,north=true,south=false,waterlogged=false,west=false]"
            },
            {
                "char": "μ",
                "block": "minecraft:iron_bars[east=false,north=false,south=true,waterlogged=false,west=false]"
            },
            {
                "char": "ν",
                "block": "minecraft:iron_bars[east=true,north=false,south=false,waterlogged=false,west=true]"
            },
            {
                "char": "ξ",
                "block": "minecraft:iron_bars[east=false,north=true,south=true,waterlogged=false,west=false]"
            },
            {
                "char": "ο",
                "block": "minecraft:iron_bars[east=false,north=false,south=false,waterlogged=false,west=false]"
            },
            {
                "char": "π",
                "block": "minecraft:iron_bars[east=true,north=true,south=true,waterlogged=false,west=false]"
            },
            {
                "char": "ρ",
                "block": "minecraft:iron_bars[east=false,north=true,south=true,waterlogged=false,west=true]"
            },
            {
                "char": "σ",
                "block": "minecraft:iron_bars[east=true,north=true,south=false,waterlogged=false,west=true]"
            },
            {
                "char": "τ",
                "block": "minecraft:iron_bars[east=true,north=false,south=true,waterlogged=false,west=true]"
            },
            {
                "char": "υ",
                "block": "create_new_age:electrical_connector[facing=up,mode=inert]"
            },
            {
                "char": "φ",
                "block": "minecraft:iron_bars[east=true,north=true,south=true,waterlogged=false,west=true]"
            }
        ]
    },
    "slices": [
        [
            "                ",
            "                ",
            "                ",
            "   αααα  αααβ   ",
            "   βααγ  αααα   ",
            "   αααα  αααα   ",
            "   αααα  βααα   ",
            "                ",
            "                ",
            "   βααα  βαβα   ",
            "   ααβα  αααα   ",
            "   αααα  βααα   ",
            "   αααα  αααα   ",
            "                ",
            "                ",
            "                "
        ],
        [
            "                ",
            "                ",
            "                ",
            "   αααα  αααα   ",
            "   αααα  αγαα   ",
            "   αααα  βααα   ",
            "   αβαγ  αααα   ",
            "                ",
            "                ",
            "   γβαα  βααα   ",
            "   αααα  αααα   ",
            "   αββα  αβαα   ",
            "   αααα  αααα   ",
            "                ",
            "                ",
            "                "
        ],
        [
            "                ",
            "                ",
            "                ",
            "   αααα  αααα   ",
            "   ααγα  αααα   ",
            "   γααγ  αααα   ",
            "   γααγ  αγαα   ",
            "                ",
            "                ",
            "   αααα  αααα   ",
            "   αααα  αααα   ",
            "   αααα  αααα   ",
            "   γααγ  αααα   ",
            "                ",
            "                ",
            "                "
        ],
        [
            "                ",
            "                ",
            "                ",
            "   αααα  αααβ   ",
            "   ααγα  βαβα   ",
            "   αααα  αααα   ",
            "   γαβα  αααα   ",
            "                ",
            "                ",
            "   αααα  αβαα   ",
            "   αααα  αααγ   ",
            "   αααα  αααγ   ",
            "   βααα  αααα   ",
            "                ",
            "                ",
            "                "
        ],
        [
            "                ",
            "                ",
            "                ",
            "                ",
            "    εα    αζ    ",
            "    α      α    ",
            "                ",
            "                ",
            "                ",
            "                ",
            "    γ      α    ",
            "    ηβ    αθ    ",
            "                ",
            "                ",
            "                ",
            "                "
        ],
        [
            "                ",
            "                ",
            "                ",
            "                ",
            "    ει    κζ    ",
            "    λ      λ    ",
            "                ",
            "                ",
            "                ",
            "                ",
            "    μ      μ    ",
            "    ηι    κθ    ",
            "                ",
            "                ",
            "                ",
            "                "
        ],
        [
            "                ",
            "                ",
            "                ",
            "                ",
            "    ει    κζ    ",
            "    λ      λ    ",
            "                ",
            "                ",
            "                ",
            "                ",
            "    μ      μ    ",
            "    ηι    κθ    ",
            "                ",
            "                ",
            "                ",
            "                "
        ],
        [
            "                ",
            "                ",
            "                ",
            "                ",
            "    εζ    εζ    ",
            "    ηθ    ηθ    ",
            "                ",
            "                ",
            "                ",
            "                ",
            "    εζ    εζ    ",
            "    ηθ    ηθ    ",
            "                ",
            "                ",
            "                ",
            "                "
        ],
        [
            "                ",
            "                ",
            "                ",
            "                ",
            "     μ    μ     ",
            "    κθ    ηι    ",
            "                ",
            "                ",
            "                ",
            "                ",
            "    κζ    ει    ",
            "     λ    λ     ",
            "                ",
            "                ",
            "                ",
            "                "
        ],
        [
            "                ",
            "                ",
            "                ",
            "                ",
            "     μ    μ     ",
            "    κθ    ηι    ",
            "                ",
            "                ",
            "                ",
            "                ",
            "    κζ    ει    ",
            "     λ    λ     ",
            "                ",
            "                ",
            "                ",
            "                "
        ],
        [
            "                ",
            "                ",
            "                ",
            "                ",
            "     εννννζ     ",
            "    εθ    ηζ    ",
            "    ξ      ξ    ",
            "    ξ      ξ    ",
            "    ξ      ξ    ",
            "    ξ      ξ    ",
            "    ηζ    εθ    ",
            "     ηννννθ     ",
            "                ",
            "                ",
            "                ",
            "                "
        ],
        [
            "                ",
            "                ",
            "                ",
            "                ",
            "                ",
            "     ο    ο     ",
            "                ",
            "                ",
            "                ",
            "                ",
            "     ο    ο     ",
            "                ",
            "                ",
            "                ",
            "                ",
            "                "
        ],
        [
            "                ",
            "                ",
            "                ",
            "                ",
            "                ",
            "     ο    ο     ",
            "                ",
            "                ",
            "                ",
            "                ",
            "     ο    ο     ",
            "                ",
            "                ",
            "                ",
            "                ",
            "                "
        ],
        [
            "                ",
            "                ",
            "                ",
            "                ",
            "                ",
            "     εννννζ     ",
            "     ξ    ξ     ",
            "     ξ    ξ     ",
            "     ξ    ξ     ",
            "     ξ    ξ     ",
            "     ηννννθ     ",
            "                ",
            "                ",
            "                ",
            "                ",
            "                "
        ],
        [
            "                ",
            "                ",
            "                ",
            "                ",
            "                ",
            "     εζ  εζ     ",
            "     ηθ  ηθ     ",
            "                ",
            "                ",
            "     εζ  εζ     ",
            "     ηθ  ηθ     ",
            "                ",
            "                ",
            "                ",
            "                ",
            "                "
        ],
        [
            "                ",
            "                ",
            "                ",
            "                ",
            "                ",
            "                ",
            "      ο  ο      ",
            "                ",
            "                ",
            "      ο  ο      ",
            "                ",
            "                ",
            "                ",
            "                ",
            "                ",
            "                "
        ],
        [
            "                ",
            "                ",
            "                ",
            "       εζ       ",
            "       πρ       ",
            "       πρ       ",
            "      εσσζ      ",
            "      ξ  ξ      ",
            "      ξ  ξ      ",
            "      ηττθ      ",
            "       πρ       ",
            "       πρ       ",
            "       ηθ       ",
            "                ",
            "                ",
            "                "
        ],
        [
            "                ",
            "                ",
            "                ",
            "       υυ       ",
            "                ",
            "                ",
            "      ο  ο      ",
            "                ",
            "                ",
            "      ο  ο      ",
            "                ",
            "                ",
            "       υυ       ",
            "                ",
            "                ",
            "                "
        ],
        [
            "                ",
            "                ",
            "                ",
            "                ",
            "       εζ       ",
            "       πρ       ",
            "      εσσζ      ",
            "      ξ  ξ      ",
            "      ξ  ξ      ",
            "      ηττθ      ",
            "       πρ       ",
            "       ηθ       ",
            "                ",
            "                ",
            "                ",
            "                "
        ],
        [
            "                ",
            "                ",
            "                ",
            "                ",
            "       υυ       ",
            "                ",
            "      ο  ο      ",
            "                ",
            "                ",
            "      ο  ο      ",
            "                ",
            "       υυ       ",
            "                ",
            "                ",
            "                ",
            "                "
        ],
        [
            "                ",
            "                ",
            "                ",
            "                ",
            "                ",
            "       εζ       ",
            "      εφφζ      ",
            "      πφφρ      ",
            "      πφφρ      ",
            "      ηφφθ      ",
            "       ηθ       ",
            "                ",
            "                ",
            "                ",
            "                ",
            "                "
        ],
        [
            "                ",
            "                ",
            "                ",
            "                ",
            "                ",
            "       υυ       ",
            "                ",
            "       εζ       ",
            "       ηθ       ",
            "                ",
            "       υυ       ",
            "                ",
            "                ",
            "                ",
            "                ",
            "                "
        ],
        [
            "                ",
            "                ",
            "                ",
            "                ",
            "                ",
            "                ",
            "                ",
            "       εζ       ",
            "       ηθ       ",
            "                ",
            "                ",
            "                ",
            "                ",
            "                ",
            "                ",
            "                "
        ],
        [
            "                ",
            "                ",
            "                ",
            "                ",
            "                ",
            "                ",
            "                ",
            "       εζ       ",
            "       ηθ       ",
            "                ",
            "                ",
            "                ",
            "                ",
            "                ",
            "                ",
            "                "
        ],
        [
            "                ",
            "                ",
            "                ",
            "                ",
            "                ",
            "                ",
            "                ",
            "       εζ       ",
            "       ηθ       ",
            "                ",
            "                ",
            "                ",
            "                ",
            "                ",
            "                ",
            "                "
        ]
    ]
}